microk8s_configure-0.0.7.data/scripts/mk8sconf.py
mk8sconfig/__init__.py
mk8sconfig/__main__.py
mk8sconfig/main.py
mk8sconfig/ssh_connection.py
microk8s_configure-0.0.7.dist-info/LICENSE
microk8s_configure-0.0.7.dist-info/METADATA
microk8s_configure-0.0.7.dist-info/WHEEL
microk8s_configure-0.0.7.dist-info/entry_points.txt
microk8s_configure-0.0.7.dist-info/top_level.txt
microk8s_configure-0.0.7.dist-info/RECORD
