Metadata-Version: 2.1
Name: microk8s-configure
Version: 0.0.7
Summary: Tool for configure microk8s on Ubuntu VPS
Home-page: https://github.com/netsaj/microk8s-configure
Author: Fabio Moreno
Author-email: fabiomoreno@outlook.com
License: MIT
Platform: UNKNOWN
Classifier: License :: OSI Approved :: MIT License
Classifier: Programming Language :: Python :: 3
Classifier: Programming Language :: Python :: 3.6
Requires-Dist: paramiko (==2.4.2)
Requires-Dist: cryptography (==2.4.2)
Requires-Dist: termcolor (==1.1.0)
Requires-Dist: tqdm (==4.31.1)
